{
  "$schema": "https://developer.microsoft.com/json-schemas/spfx-build/spfx-serve.schema.json",
  "port": 4321,
  "https": true,
  "serveConfigurations": {
    "default": {
      "pageUrl": "https://{tenantDomain}/SitePages/myPage.aspx",
      "customActions": {
        "fcd6b761-bb08-4e6c-acfc-9d082b1878f5": {
          "location": "ClientSideExtension.ApplicationCustomizer",
          "properties": {
            "message": "Simple header application customizer"
          }
        }
      }
    },
    "headerApplicationCustomizer": {
      "pageUrl": "https://{tenantDomain}/SitePages/myPage.aspx",
      "customActions": {
        "fcd6b761-bb08-4e6c-acfc-9d082b1878f5": {
          "location": "ClientSideExtension.ApplicationCustomizer",
          "properties": {
            "message": "Simple header application customizer"
          }
        }
      }
    }
  }
}
